alertlogic_sdk_definitions-0.1.165.dist-info/licenses/LICENSE
alsdkdefs/__init__.py
alsdkdefs/version.py
alsdkdefs/apis/aecontent/aecontent.v1.yaml
alsdkdefs/apis/aefr/aefr.v1.yaml
alsdkdefs/apis/aemanual/aemanual.v1.yaml
alsdkdefs/apis/aepublish/aepublish.v1.yaml
alsdkdefs/apis/aerta/aerta.v1.yaml
alsdkdefs/apis/aetag/aetag.v1.yaml
alsdkdefs/apis/aetuner/aetuner.v1.yaml
alsdkdefs/apis/aims/aims.v1.yaml
alsdkdefs/apis/assets_manager/assets_manager.v1.yaml
alsdkdefs/apis/assets_manager/api/assets_manager.v1.html
alsdkdefs/apis/assets_query/assets_query.v1.yaml
alsdkdefs/apis/assets_query/examples.yaml
alsdkdefs/apis/assets_query/parameters.yaml
alsdkdefs/apis/assets_query/remediations.v1.yaml
alsdkdefs/apis/assets_query/responses.yaml
alsdkdefs/apis/assets_query/schemas.yaml
alsdkdefs/apis/assets_write/assets_write.v1.yaml
alsdkdefs/apis/assets_write/examples.yaml
alsdkdefs/apis/cargo/cargo.v2.yaml
alsdkdefs/apis/connectors/connectors.v1.yaml
alsdkdefs/apis/credentials/credentials.v2.yaml
alsdkdefs/apis/deployments/deployments.v1.yaml
alsdkdefs/apis/endpoints/endpoints.v1.yaml
alsdkdefs/apis/herald/herald.v1.yaml
alsdkdefs/apis/ingest/ingest.v1.yaml
alsdkdefs/apis/iris/iris.v3.yaml
alsdkdefs/apis/kalm/kalm.v1.yaml
alsdkdefs/apis/notify/notify.v3.yaml
alsdkdefs/apis/otis/otis.v3.yaml
alsdkdefs/apis/otis/api/otis.v3.html
alsdkdefs/apis/policies/policies.v1.yaml
alsdkdefs/apis/remediations/assets_query.v1.yaml
alsdkdefs/apis/remediations/examples.yaml
alsdkdefs/apis/remediations/parameters.yaml
alsdkdefs/apis/remediations/remediations.v1.yaml
alsdkdefs/apis/remediations/responses.yaml
alsdkdefs/apis/remediations/schemas.yaml
alsdkdefs/apis/responder/Makefile
alsdkdefs/apis/responder/responder.v1.yaml
alsdkdefs/apis/scan_scheduler/scan_scheduler.v2.yaml
alsdkdefs/apis/scan_scheduler/api/scan_scheduler.v2.html
alsdkdefs/apis/search/search.v2.yaml
alsdkdefs/apis/search_stylist/search_stylist.v1.yaml
alsdkdefs/apis/subscriptions/subscriptions.v1.yaml
alsdkdefs/apis/suggestions/suggestions.v1.yaml
alsdkdefs/apis/themis/themis.v1.yaml
alertlogic_sdk_definitions-0.1.165.dist-info/METADATA
alertlogic_sdk_definitions-0.1.165.dist-info/WHEEL
alertlogic_sdk_definitions-0.1.165.dist-info/top_level.txt
alertlogic_sdk_definitions-0.1.165.dist-info/RECORD
