Metadata-Version: 2.4
Name: alertlogic-sdk-definitions
Version: 0.1.165
Summary: The Alert Logic API definitions.
Home-page: https://github.com/alertlogic/alertlogic-sdk-definitions
Author: Alert Logic Inc.
Author-email: devsupport@alertlogic.com
License: MIT license
Keywords: alcli,almdr,alsdkdefs,alertlogic,alertlogic-cli
Platform: any
Classifier: Development Status :: 3 - Alpha
Classifier: Intended Audience :: Developers
Classifier: License :: OSI Approved :: MIT License
Classifier: Natural Language :: English
Classifier: Programming Language :: Python :: 3.6
Classifier: Programming Language :: Python :: 3.7
Classifier: Programming Language :: Python :: 3.8
Requires-Python: >=3.6
License-File: LICENSE
Requires-Dist: jsonschema[format_nongpl]==3.2.0
Requires-Dist: pyyaml>=5.4.1
Requires-Dist: requests>=2.18
Requires-Dist: urllib3<2
Requires-Dist: jsonmerge>=1.8.0
Provides-Extra: dev
Requires-Dist: pytest>=3; extra == "dev"
Requires-Dist: mock>=2.0.0; extra == "dev"
Requires-Dist: httpretty>=0.8.14; extra == "dev"
Requires-Dist: pycodestyle>=2.3.1; extra == "dev"
Requires-Dist: jsonmerge>=1.8.0; extra == "dev"
Dynamic: author
Dynamic: author-email
Dynamic: classifier
Dynamic: description
Dynamic: description-content-type
Dynamic: home-page
Dynamic: keywords
Dynamic: license
Dynamic: license-file
Dynamic: platform
Dynamic: provides-extra
Dynamic: requires-dist
Dynamic: requires-python
Dynamic: summary
